linear/__init__.py
linear/admin.py
linear/apps.py
linear/management/commands/import_issues.py
linear/migrations/0001_initial.py
linear/migrations/__init__.py
linear/models.py
linear/queries.py
linear/templates/admin/linear/change_form.html
linear/templates/admin/linear/change_form_object_tools.html
linear/templates/admin/linear/change_list_object_tools.html
linear/urls.py
linear/views.py
django_linear-0.2.0.dist-info/LICENSE
django_linear-0.2.0.dist-info/WHEEL
django_linear-0.2.0.dist-info/METADATA
django_linear-0.2.0.dist-info/RECORD
