Metadata-Version: 2.1
Name: django-linear
Version: 0.2.0
Summary: Django app for importing Linear issues into the Django admin site.
Home-page: https://github.com/yunojuno/django-linear
License: MIT
Author: YunoJuno
Author-email: code@yunojuno.com
Maintainer: YunoJuno
Maintainer-email: code@yunojuno.com
Requires-Python: >=3.7,<4.0
Classifier: Development Status :: 4 - Beta
Classifier: Environment :: Web Environment
Classifier: Framework :: Django
Classifier: Framework :: Django :: 3.0
Classifier: Framework :: Django :: 3.1
Classifier: License :: OSI Approved :: MIT License
Classifier: Operating System :: OS Independent
Classifier: Programming Language :: Python :: 3
Classifier: Programming Language :: Python :: 3 :: Only
Classifier: Programming Language :: Python :: 3.7
Classifier: Programming Language :: Python :: 3.8
Provides-Extra: heroku
Requires-Dist: dj_database_url; extra == "heroku"
Requires-Dist: django (>=3.0,<4.0)
Requires-Dist: gunicorn; extra == "heroku"
Requires-Dist: psycopg2; extra == "heroku"
Requires-Dist: requests
Requires-Dist: whitenoise; extra == "heroku"
Project-URL: Documentation, https://github.com/yunojuno/django-linear
Project-URL: Repository, https://github.com/yunojuno/django-linear
